LevityDash/__init__.py
LevityDash/__main__.py
LevityDash/example-config/config.ini
LevityDash/example-config/fonts/Nunito/Nunito-Italic-VariableFont_wght.ttf
LevityDash/example-config/fonts/Nunito/Nunito-VariableFont_wght.ttf
LevityDash/example-config/fonts/Nunito/OFL.txt
LevityDash/example-config/fonts/Nunito/README.txt
LevityDash/example-config/fonts/Nunito/static/Nunito-Black.ttf
LevityDash/example-config/fonts/Nunito/static/Nunito-BlackItalic.ttf
LevityDash/example-config/fonts/Nunito/static/Nunito-Bold.ttf
LevityDash/example-config/fonts/Nunito/static/Nunito-BoldItalic.ttf
LevityDash/example-config/fonts/Nunito/static/Nunito-ExtraBold.ttf
LevityDash/example-config/fonts/Nunito/static/Nunito-ExtraBoldItalic.ttf
LevityDash/example-config/fonts/Nunito/static/Nunito-ExtraLight.ttf
LevityDash/example-config/fonts/Nunito/static/Nunito-ExtraLightItalic.ttf
LevityDash/example-config/fonts/Nunito/static/Nunito-Italic.ttf
LevityDash/example-config/fonts/Nunito/static/Nunito-Light.ttf
LevityDash/example-config/fonts/Nunito/static/Nunito-LightItalic.ttf
LevityDash/example-config/fonts/Nunito/static/Nunito-Medium.ttf
LevityDash/example-config/fonts/Nunito/static/Nunito-MediumItalic.ttf
LevityDash/example-config/fonts/Nunito/static/Nunito-Regular.ttf
LevityDash/example-config/fonts/Nunito/static/Nunito-SemiBold.ttf
LevityDash/example-config/fonts/Nunito/static/Nunito-SemiBoldItalic.ttf
LevityDash/example-config/fonts/weathericons.ttf
LevityDash/example-config/plugins/Govee/config.ini
LevityDash/example-config/plugins/WeatherFlow.ini
LevityDash/example-config/plugins/plugins.ini
LevityDash/example-config/saves/dashboards/default.levity
LevityDash/example-config/templates/dashboards/Empty.levity
LevityDash/example-config/templates/dashboards/OpenMeteo.levity
LevityDash/example-config/templates/dashboards/WeatherFlow.levity
LevityDash/example-config/templates/panels/Clock.levityPanel
LevityDash/lib/EasyPath.py
LevityDash/lib/__init__.py
LevityDash/lib/config.py
levitydash-0.1.0b10.dist-info/entry_points.txt
levitydash-0.1.0b10.dist-info/LICENSE.txt
levitydash-0.1.0b10.dist-info/WHEEL
levitydash-0.1.0b10.dist-info/METADATA
levitydash-0.1.0b10.dist-info/RECORD
