Metadata-Version: 2.1
Name: levitydash
Version: 0.1.0b10
Summary: A lightweight, desktop native, multi-source, modulear dashboard for macOS, Windows and Linux
Home-page: https://levitydash.app
License: MIT
Keywords: dashboard,desktop,app,weather,dash
Author: noblecloud
Author-email: git@noblecloud.io
Requires-Python: >=3.10,<3.11
Classifier: Development Status :: 4 - Beta
Classifier: Environment :: Plugins
Classifier: Framework :: AsyncIO
Classifier: Framework :: aiohttp
Classifier: Intended Audience :: Developers
Classifier: Intended Audience :: Education
Classifier: Intended Audience :: End Users/Desktop
Classifier: Intended Audience :: Information Technology
Classifier: License :: OSI Approved :: MIT License
Classifier: Natural Language :: English
Classifier: Operating System :: OS Independent
Classifier: Programming Language :: Python :: 3
Classifier: Programming Language :: Python :: 3.10
Classifier: Programming Language :: Python :: 3.10
Classifier: Topic :: Desktop Environment
Classifier: Topic :: Utilities
Requires-Dist: PySide2 (>=5.15.2,<6.0.0)
Requires-Dist: PyYAML (>=6.0,<7.0)
Requires-Dist: WeatherUnits (>=0.6.3,<0.7.0)
Requires-Dist: aiohttp (>=3.8.1,<4.0.0)
Requires-Dist: appdirs (>=1.4.4,<2.0.0)
Requires-Dist: bleak (>=0.14.2,<0.15.0)
Requires-Dist: numpy (>=1.18.0,<2.0.0)
Requires-Dist: pylunar (>=0.6.0,<0.7.0)
Requires-Dist: pysolar (>=0.10,<0.11)
Requires-Dist: python-dateutil (>=2.8.2,<3.0.0)
Requires-Dist: pytz (>=2022.1,<2023.0)
Requires-Dist: qasync (>=0.23.0,<0.24.0)
Requires-Dist: rich (>=12.3.0,<13.0.0)
Requires-Dist: scipy (>=1.8.0,<2.0.0)
Project-URL: Bug Tracker, https://github.com/noblecloud/LevityDash/issues
Project-URL: Documentation, https://levitydash.app/#/getting-started
Project-URL: Discussions, https://github.com/noblecloud/LevityDash/discussions
Project-URL: Repository, https://github.com/noblecloud/LevityDash
